setup.py
gpiosvr/__init__.py
gpiosvr/test_led_app.py
gpiosvr.egg-info/PKG-INFO
gpiosvr.egg-info/SOURCES.txt
gpiosvr.egg-info/dependency_links.txt
gpiosvr.egg-info/requires.txt
gpiosvr.egg-info/top_level.txt
gpiosvr/led/__init__.py
gpiosvr/led/app.py
gpiosvr/led/resources.py