Metadata-Version: 1.2
Name: gpiosvr
Version: 0.0.3
Summary: RESTful interfaces for Raspberry Pi GPIO
Home-page: https://github.com/projectweekend/gpiosvr
Author: Brian Hines
Author-email: brian@projectweekend.net
License: MIT
Platform: UNKNOWN
Requires-Python: >=3
